dicom_image_reader/__init__.py
dicom_image_reader/read_image.py
dicom_image_reader-0.0.2.dist-info/METADATA
dicom_image_reader-0.0.2.dist-info/WHEEL
dicom_image_reader-0.0.2.dist-info/top_level.txt
dicom_image_reader-0.0.2.dist-info/RECORD
